jankigen/__init__.py
jankigen/__main__.py
jankigen/card_gen.py
jankigen/cli_utils.py
jankigen/deck_gen.py
jankigen/favicon.ico
jankigen/gui.py
jankigen/learning_material_getter.py
jankigen/version.py
jankigen/db/jamdict.db
jankigen-0.1.3.dist-info/LICENSE
jankigen-0.1.3.dist-info/METADATA
jankigen-0.1.3.dist-info/WHEEL
jankigen-0.1.3.dist-info/entry_points.txt
jankigen-0.1.3.dist-info/top_level.txt
jankigen-0.1.3.dist-info/RECORD
