Metadata-Version: 2.1
Name: jankigen
Version: 0.1.3
Summary: Generate Anki decks from Japanese text
Home-page: UNKNOWN
License: UNKNOWN
Platform: UNKNOWN
Requires-Dist: genanki
Requires-Dist: jamdict
Requires-Dist: janome
Requires-Dist: ttkthemes
